{
  "course_code": "FIN 629",
  "course_title": "Fixed Income Portfolio Management",
  "subject": "FIN",
  "catalog_number": "629",
  "term": "Fall_2026",
  "srcdb": "5269",
  "credit_hours": null,
  "requirement_designation": null,
  "course_description": null,
  "course_notes": null,
  "requisites": null,
  "cross_listed": null,
  "date_range": {
    "start": "2026-08-26",
    "end": "2026-12-09"
  },
  "sections": [
    {
      "crn": "3691",
      "section_number": "2136",
      "schedule_type": "LEC",
      "instructor": "N. Valerio III",
      "instructors": [
        {
          "name": "N. Valerio III",
          "email": null
        }
      ],
      "location": null,
      "enrollment_status": "Open",
      "enrollment_count": "2",
      "is_cancelled": false,
      "schedule": {
        "display": "T 6:30-9:30p",
        "meetings": [
          {
            "day": "Tue",
            "start": "1830",
            "end": "2130"
          }
        ]
      }
    },
    {
      "crn": "3692",
      "section_number": "3236",
      "schedule_type": "LEC",
      "instructor": "N. Valerio III",
      "instructors": [
        {
          "name": "N. Valerio III",
          "email": null
        }
      ],
      "location": null,
      "enrollment_status": "Closed",
      "enrollment_count": "2",
      "is_cancelled": false,
      "schedule": {
        "display": "T 6:30-9:30p",
        "meetings": [
          {
            "day": "Tue",
            "start": "1830",
            "end": "2130"
          }
        ]
      }
    }
  ],
  "section_summary": {
    "total_sections": 2,
    "lectures": 2,
    "labs": 0,
    "discussions": 0,
    "other": 0,
    "open": 1,
    "closed": 1,
    "waitlisted": 0
  },
  "instructors_unique": [
    "N. Valerio III"
  ],
  "scraped_at": "2026-05-13T00:40:16.047Z"
}