{
  "course_code": "MESAS 225",
  "course_title": "South Asian Food and Diaspora",
  "subject": "MESAS",
  "catalog_number": "225",
  "term": "Spring_2026",
  "srcdb": "5261",
  "credit_hours": "3",
  "requirement_designation": "HA",
  "requirements": [
    "HA"
  ],
  "campus": null,
  "campus_description": null,
  "course_description": "The course examines the rich tapestry of South Asian cuisine, examining how it has evolved and spread across the globe through migration. It also examines the South Asian diaspora's influence on global food cultures, focusing on and the emergence of new culinary expressions.",
  "course_notes": null,
  "requisites": null,
  "cross_listed": null,
  "date_range": {
    "start": "2026-01-13",
    "end": "2026-04-27"
  },
  "sections": [
    {
      "crn": "2605",
      "section_number": "1",
      "schedule_type": "LEC",
      "instructor": "K. Singh",
      "instructors": [
        {
          "name": "K. Singh",
          "email": null
        }
      ],
      "location": null,
      "campus": null,
      "campus_description": null,
      "requirement_designation": null,
      "requirements": [],
      "enrollment_status": "Open",
      "enrollment_count": "1",
      "is_cancelled": false,
      "schedule": {
        "display": "TTh 2:30-3:45p",
        "meetings": [
          {
            "day": "Tue",
            "start": "1430",
            "end": "1545"
          },
          {
            "day": "Thu",
            "start": "1430",
            "end": "1545"
          }
        ]
      }
    },
    {
      "crn": "2605",
      "section_number": "1",
      "schedule_type": "LEC",
      "instructor": "K. Singh",
      "instructors": [
        {
          "name": "K. Singh",
          "email": null
        }
      ],
      "location": null,
      "campus": "Oxford",
      "campus_description": "Oxford",
      "requirement_designation": null,
      "requirements": [],
      "enrollment_status": "Open",
      "enrollment_count": "1",
      "is_cancelled": false,
      "schedule": {
        "display": "TTh 2:30-3:45p",
        "meetings": [
          {
            "day": "Tue",
            "start": "1430",
            "end": "1545"
          },
          {
            "day": "Thu",
            "start": "1430",
            "end": "1545"
          }
        ]
      }
    }
  ],
  "section_summary": {
    "total_sections": 2,
    "lectures": 2,
    "labs": 0,
    "discussions": 0,
    "other": 0,
    "open": 2,
    "closed": 0,
    "waitlisted": 0
  },
  "instructors_unique": [
    "K. Singh"
  ],
  "scraped_at": "2026-06-17T23:03:57.662Z"
}