{
  "course_code": "SOC 101",
  "course_title": "Intro to General Sociology",
  "subject": "SOC",
  "catalog_number": "101",
  "term": "Spring_2026",
  "srcdb": "5261",
  "credit_hours": "3",
  "requirement_designation": "SS",
  "course_description": "Study of human social behavior. Social and cultural aspects of the emergence, maintenance, modification, and adjustment of human groups.",
  "course_notes": null,
  "requisites": null,
  "cross_listed": null,
  "date_range": {
    "start": "2026-01-13",
    "end": "2026-04-27"
  },
  "sections": [
    {
      "crn": "3028",
      "section_number": "1",
      "schedule_type": "LEC",
      "instructor": "A. Barra",
      "instructors": [
        {
          "name": "A. Barra",
          "email": null
        }
      ],
      "location": null,
      "enrollment_status": "Open",
      "enrollment_count": "3",
      "is_cancelled": false,
      "schedule": {
        "display": "MW 5:30-6:45p",
        "meetings": [
          {
            "day": "Mon",
            "start": "1730",
            "end": "1845"
          },
          {
            "day": "Wed",
            "start": "1730",
            "end": "1845"
          }
        ]
      }
    },
    {
      "crn": "3032",
      "section_number": "2",
      "schedule_type": "LEC",
      "instructor": "A. Barra",
      "instructors": [
        {
          "name": "A. Barra",
          "email": null
        }
      ],
      "location": null,
      "enrollment_status": "Open",
      "enrollment_count": "3",
      "is_cancelled": false,
      "schedule": {
        "display": "TTh 2:30-3:45p",
        "meetings": [
          {
            "day": "Tue",
            "start": "1430",
            "end": "1545"
          },
          {
            "day": "Thu",
            "start": "1430",
            "end": "1545"
          }
        ]
      }
    },
    {
      "crn": "3040",
      "section_number": "3",
      "schedule_type": "LEC",
      "instructor": "T. Scott",
      "instructors": [
        {
          "name": "T. Scott",
          "email": null
        }
      ],
      "location": null,
      "enrollment_status": "Open",
      "enrollment_count": "3",
      "is_cancelled": false,
      "schedule": {
        "display": "TTh 10-11:15a",
        "meetings": [
          {
            "day": "Tue",
            "start": "1000",
            "end": "1115"
          },
          {
            "day": "Thu",
            "start": "1000",
            "end": "1115"
          }
        ]
      }
    }
  ],
  "section_summary": {
    "total_sections": 3,
    "lectures": 3,
    "labs": 0,
    "discussions": 0,
    "other": 0,
    "open": 3,
    "closed": 0,
    "waitlisted": 0
  },
  "instructors_unique": [
    "A. Barra",
    "T. Scott"
  ],
  "scraped_at": "2026-05-13T00:39:12.874Z"
}