{
  "course_code": "SOC 497R",
  "course_title": "Directed Research",
  "subject": "SOC",
  "catalog_number": "497R",
  "term": "Spring_2026",
  "srcdb": "5261",
  "credit_hours": "1 - 12",
  "requirement_designation": "XA",
  "requirements": [
    "XA"
  ],
  "campus": null,
  "campus_description": null,
  "course_description": "Supervised work on a faculty member's research project, normally for students who have demonstrated superior performance in sociology.",
  "course_notes": null,
  "requisites": null,
  "cross_listed": null,
  "date_range": {
    "start": "2026-01-13",
    "end": "2026-04-27"
  },
  "sections": [
    {
      "crn": "3112",
      "section_number": "1",
      "schedule_type": "RSC",
      "instructor": "R. Franzosi",
      "instructors": [
        {
          "name": "R. Franzosi",
          "email": null
        }
      ],
      "location": null,
      "campus": null,
      "campus_description": null,
      "requirement_designation": null,
      "requirements": [],
      "enrollment_status": "Open",
      "enrollment_count": "9",
      "is_cancelled": false,
      "schedule": {
        "display": "Does Not Meet",
        "meetings": []
      }
    },
    {
      "crn": "6392",
      "section_number": "2",
      "schedule_type": "RSC",
      "instructor": "K. Brown",
      "instructors": [
        {
          "name": "K. Brown",
          "email": null
        }
      ],
      "location": null,
      "campus": null,
      "campus_description": null,
      "requirement_designation": null,
      "requirements": [],
      "enrollment_status": "Waitlist",
      "enrollment_count": "9",
      "is_cancelled": false,
      "schedule": {
        "display": "Does Not Meet",
        "meetings": []
      }
    },
    {
      "crn": "6481",
      "section_number": "3",
      "schedule_type": "RSC",
      "instructor": "R. Hall-Clifford",
      "instructors": [
        {
          "name": "R. Hall-Clifford",
          "email": null
        }
      ],
      "location": null,
      "campus": null,
      "campus_description": null,
      "requirement_designation": null,
      "requirements": [],
      "enrollment_status": "Open",
      "enrollment_count": "9",
      "is_cancelled": false,
      "schedule": {
        "display": "Does Not Meet",
        "meetings": []
      }
    },
    {
      "crn": "6482",
      "section_number": "4",
      "schedule_type": "RSC",
      "instructor": "N. Hoffmann",
      "instructors": [
        {
          "name": "N. Hoffmann",
          "email": null
        }
      ],
      "location": null,
      "campus": null,
      "campus_description": null,
      "requirement_designation": null,
      "requirements": [],
      "enrollment_status": "Open",
      "enrollment_count": "9",
      "is_cancelled": false,
      "schedule": {
        "display": "Does Not Meet",
        "meetings": []
      }
    },
    {
      "crn": "6531",
      "section_number": "5",
      "schedule_type": "RSC",
      "instructor": "C. Puckett",
      "instructors": [
        {
          "name": "C. Puckett",
          "email": null
        }
      ],
      "location": null,
      "campus": null,
      "campus_description": null,
      "requirement_designation": null,
      "requirements": [],
      "enrollment_status": "Open",
      "enrollment_count": "9",
      "is_cancelled": false,
      "schedule": {
        "display": "Does Not Meet",
        "meetings": []
      }
    },
    {
      "crn": "6555",
      "section_number": "6",
      "schedule_type": "RSC",
      "instructor": "B. Xu",
      "instructors": [
        {
          "name": "B. Xu",
          "email": null
        }
      ],
      "location": null,
      "campus": null,
      "campus_description": null,
      "requirement_designation": null,
      "requirements": [],
      "enrollment_status": "Open",
      "enrollment_count": "9",
      "is_cancelled": false,
      "schedule": {
        "display": "Does Not Meet",
        "meetings": []
      }
    },
    {
      "crn": "6556",
      "section_number": "7",
      "schedule_type": "RSC",
      "instructor": "E. Idler",
      "instructors": [
        {
          "name": "E. Idler",
          "email": null
        }
      ],
      "location": null,
      "campus": null,
      "campus_description": null,
      "requirement_designation": null,
      "requirements": [],
      "enrollment_status": "Open",
      "enrollment_count": "9",
      "is_cancelled": false,
      "schedule": {
        "display": "Does Not Meet",
        "meetings": []
      }
    },
    {
      "crn": "6585",
      "section_number": "8",
      "schedule_type": "RSC",
      "instructor": "A. Sewell",
      "instructors": [
        {
          "name": "A. Sewell",
          "email": null
        }
      ],
      "location": null,
      "campus": null,
      "campus_description": null,
      "requirement_designation": null,
      "requirements": [],
      "enrollment_status": "Open",
      "enrollment_count": "9",
      "is_cancelled": false,
      "schedule": {
        "display": "Does Not Meet",
        "meetings": []
      }
    },
    {
      "crn": "6625",
      "section_number": "9",
      "schedule_type": "RSC",
      "instructor": "J. Mullis",
      "instructors": [
        {
          "name": "J. Mullis",
          "email": null
        }
      ],
      "location": null,
      "campus": null,
      "campus_description": null,
      "requirement_designation": null,
      "requirements": [],
      "enrollment_status": "Open",
      "enrollment_count": "9",
      "is_cancelled": false,
      "schedule": {
        "display": "Does Not Meet",
        "meetings": []
      }
    },
    {
      "crn": "3112",
      "section_number": "1",
      "schedule_type": "RSC",
      "instructor": "R. Franzosi",
      "instructors": [
        {
          "name": "R. Franzosi",
          "email": null
        }
      ],
      "location": null,
      "campus": "Oxford",
      "campus_description": "Oxford",
      "requirement_designation": null,
      "requirements": [],
      "enrollment_status": "Open",
      "enrollment_count": "9",
      "is_cancelled": false,
      "schedule": {
        "display": "Does Not Meet",
        "meetings": []
      }
    },
    {
      "crn": "6392",
      "section_number": "2",
      "schedule_type": "RSC",
      "instructor": "K. Brown",
      "instructors": [
        {
          "name": "K. Brown",
          "email": null
        }
      ],
      "location": null,
      "campus": "Oxford",
      "campus_description": "Oxford",
      "requirement_designation": null,
      "requirements": [],
      "enrollment_status": "Waitlist",
      "enrollment_count": "9",
      "is_cancelled": false,
      "schedule": {
        "display": "Does Not Meet",
        "meetings": []
      }
    },
    {
      "crn": "6481",
      "section_number": "3",
      "schedule_type": "RSC",
      "instructor": "R. Hall-Clifford",
      "instructors": [
        {
          "name": "R. Hall-Clifford",
          "email": null
        }
      ],
      "location": null,
      "campus": "Oxford",
      "campus_description": "Oxford",
      "requirement_designation": null,
      "requirements": [],
      "enrollment_status": "Open",
      "enrollment_count": "9",
      "is_cancelled": false,
      "schedule": {
        "display": "Does Not Meet",
        "meetings": []
      }
    },
    {
      "crn": "6482",
      "section_number": "4",
      "schedule_type": "RSC",
      "instructor": "N. Hoffmann",
      "instructors": [
        {
          "name": "N. Hoffmann",
          "email": null
        }
      ],
      "location": null,
      "campus": "Oxford",
      "campus_description": "Oxford",
      "requirement_designation": null,
      "requirements": [],
      "enrollment_status": "Open",
      "enrollment_count": "9",
      "is_cancelled": false,
      "schedule": {
        "display": "Does Not Meet",
        "meetings": []
      }
    },
    {
      "crn": "6531",
      "section_number": "5",
      "schedule_type": "RSC",
      "instructor": "C. Puckett",
      "instructors": [
        {
          "name": "C. Puckett",
          "email": null
        }
      ],
      "location": null,
      "campus": "Oxford",
      "campus_description": "Oxford",
      "requirement_designation": null,
      "requirements": [],
      "enrollment_status": "Open",
      "enrollment_count": "9",
      "is_cancelled": false,
      "schedule": {
        "display": "Does Not Meet",
        "meetings": []
      }
    },
    {
      "crn": "6555",
      "section_number": "6",
      "schedule_type": "RSC",
      "instructor": "B. Xu",
      "instructors": [
        {
          "name": "B. Xu",
          "email": null
        }
      ],
      "location": null,
      "campus": "Oxford",
      "campus_description": "Oxford",
      "requirement_designation": null,
      "requirements": [],
      "enrollment_status": "Open",
      "enrollment_count": "9",
      "is_cancelled": false,
      "schedule": {
        "display": "Does Not Meet",
        "meetings": []
      }
    },
    {
      "crn": "6556",
      "section_number": "7",
      "schedule_type": "RSC",
      "instructor": "E. Idler",
      "instructors": [
        {
          "name": "E. Idler",
          "email": null
        }
      ],
      "location": null,
      "campus": "Oxford",
      "campus_description": "Oxford",
      "requirement_designation": null,
      "requirements": [],
      "enrollment_status": "Open",
      "enrollment_count": "9",
      "is_cancelled": false,
      "schedule": {
        "display": "Does Not Meet",
        "meetings": []
      }
    },
    {
      "crn": "6585",
      "section_number": "8",
      "schedule_type": "RSC",
      "instructor": "A. Sewell",
      "instructors": [
        {
          "name": "A. Sewell",
          "email": null
        }
      ],
      "location": null,
      "campus": "Oxford",
      "campus_description": "Oxford",
      "requirement_designation": null,
      "requirements": [],
      "enrollment_status": "Open",
      "enrollment_count": "9",
      "is_cancelled": false,
      "schedule": {
        "display": "Does Not Meet",
        "meetings": []
      }
    },
    {
      "crn": "6625",
      "section_number": "9",
      "schedule_type": "RSC",
      "instructor": "J. Mullis",
      "instructors": [
        {
          "name": "J. Mullis",
          "email": null
        }
      ],
      "location": null,
      "campus": "Oxford",
      "campus_description": "Oxford",
      "requirement_designation": null,
      "requirements": [],
      "enrollment_status": "Open",
      "enrollment_count": "9",
      "is_cancelled": false,
      "schedule": {
        "display": "Does Not Meet",
        "meetings": []
      }
    }
  ],
  "section_summary": {
    "total_sections": 18,
    "lectures": 0,
    "labs": 0,
    "discussions": 0,
    "other": 18,
    "open": 16,
    "closed": 0,
    "waitlisted": 2
  },
  "instructors_unique": [
    "A. Sewell",
    "B. Xu",
    "C. Puckett",
    "E. Idler",
    "J. Mullis",
    "K. Brown",
    "N. Hoffmann",
    "R. Franzosi",
    "R. Hall-Clifford"
  ],
  "scraped_at": "2026-06-17T23:06:47.073Z"
}