{
  "course_code": "CPLT 190",
  "course_title": "Fresh Sem: Literature: The Philosophical Animal",
  "subject": "CPLT",
  "catalog_number": "190",
  "term": "Fall_2026",
  "srcdb": "5269",
  "credit_hours": "3",
  "requirement_designation": "FS",
  "course_description": "Freshman-only seminar designed to engage students in various aspects of inquiry and research with the close guidance of a faculty member.",
  "course_notes": null,
  "requisites": null,
  "cross_listed": null,
  "date_range": {
    "start": "2026-08-26",
    "end": "2026-12-09"
  },
  "sections": [
    {
      "crn": "2312",
      "section_number": "1",
      "schedule_type": "SEM",
      "instructor": "S. Meighoo",
      "instructors": [
        {
          "name": "S. Meighoo",
          "email": null
        }
      ],
      "location": null,
      "enrollment_status": "Closed",
      "enrollment_count": "1",
      "is_cancelled": false,
      "schedule": {
        "display": "MW 1-2:15p",
        "meetings": [
          {
            "day": "Mon",
            "start": "1300",
            "end": "1415"
          },
          {
            "day": "Wed",
            "start": "1300",
            "end": "1415"
          }
        ]
      }
    }
  ],
  "section_summary": {
    "total_sections": 1,
    "lectures": 0,
    "labs": 0,
    "discussions": 0,
    "other": 1,
    "open": 0,
    "closed": 1,
    "waitlisted": 0
  },
  "instructors_unique": [
    "S. Meighoo"
  ],
  "scraped_at": "2026-05-13T00:39:53.437Z"
}