{
  "course_code": "ENVS 190",
  "course_title": "Fresh Sem:Environmentl Studies: Interpreting Unseen Behavior",
  "subject": "ENVS",
  "catalog_number": "190",
  "term": "Fall_2026",
  "srcdb": "5269",
  "credit_hours": "3",
  "requirement_designation": "FS",
  "course_description": "The topics for freshman seminars are variable and change every semester. Past offerings include Climate Change, Global Earth Systems, Interpreting Behavior That You Can't See, Ecological Economics, Plants, People and Places and Ecological Restoration.",
  "course_notes": null,
  "requisites": null,
  "cross_listed": null,
  "date_range": {
    "start": "2026-08-26",
    "end": "2026-12-09"
  },
  "sections": [
    {
      "crn": "1904",
      "section_number": "1",
      "schedule_type": "SEM",
      "instructor": "A. Martin",
      "instructors": [
        {
          "name": "A. Martin",
          "email": null
        }
      ],
      "location": null,
      "enrollment_status": "Closed",
      "enrollment_count": "1",
      "is_cancelled": false,
      "schedule": {
        "display": "MW 11:30a-12:45p",
        "meetings": [
          {
            "day": "Mon",
            "start": "1130",
            "end": "1245"
          },
          {
            "day": "Wed",
            "start": "1130",
            "end": "1245"
          }
        ]
      }
    }
  ],
  "section_summary": {
    "total_sections": 1,
    "lectures": 0,
    "labs": 0,
    "discussions": 0,
    "other": 1,
    "open": 0,
    "closed": 1,
    "waitlisted": 0
  },
  "instructors_unique": [
    "A. Martin"
  ],
  "scraped_at": "2026-05-13T00:40:11.206Z"
}